codemapai/__init__.py
codemapai/__main__.py
codemapai/gpt.py
codemapai/main.py
codemapai/setup.py
codemapai-0.3.0.dist-info/METADATA
codemapai-0.3.0.dist-info/WHEEL
codemapai-0.3.0.dist-info/entry_points.txt
codemapai-0.3.0.dist-info/top_level.txt
codemapai-0.3.0.dist-info/RECORD
